{
  "add": "Adăugare",
  "appleIPSTooltip": "Activarea Apple IPS permite utilizatorului să utilizeze implementarea Apple IPS în cadrul facilității.",
  "addService": "Adăugați serviciu",
  "browseServiceHeading": "Alegeți un serviciu de poziționare a datelor în interior",
  "cancel": "Anulare",
  "configuration": "Configurație",
  "distance": "Distanță",
  "enableAppleIps": "Activare Apple IPS",
  "enableGNSS": "Activare GNSS",
  "enablePathSnapping": "Activare alipire la traseu",
  "enableSmoothing": "Activare netezire",
  "feet": "Ft",
  "gnssTooltip": "Activarea GNSS permite utilizatorului să obțină o poziție exterioară la ieșirea din clădire.",
  "indoorLayers": "Straturi tematice de interior",
  "indoorPositioning": "Localizare în interior",
  "indoorPositioningData": "Date de poziționare în interior",
  "meters": "Metri",
  "moreInfo": "Informații suplimentare",
  "pathSnappingTooltip": "Dacă funcția de alipire la traseu este activată, ArcGIS IPS aliniază indicatorul de poziție al utilizatorului la elementele liniare de tip traseu care sunt compatibile cu IPS.",
  "preview": "Previzualizare",
  "remove": "Eliminare",
  "restoreDefaults": "Restabilire valori implicite",
  "smoothingTooltip": "Funcția de netezire îmbunătățește navigația pas cu pas, corectând schimbările bruște de direcție, viteză și poziție."
}
